sanic_boot/Config.py
sanic_boot/__init__.py
sanic_boot/manager.py
sanic_boot/py.typed
sanic_boot/core/Controller.py
sanic_boot/core/RequestMapping.py
sanic_boot/core/Task.py
sanic_boot/core/__init__.py
sanic_boot/projectTemplate/config.ini
sanic_boot/projectTemplate/main.py
sanic_boot/projectTemplate/Controller/TestController.py
sanic_boot/projectTemplate/Models/TestModel.py
sanic_boot/projectTemplate/Models/__init__.py
sanic_boot/projectTemplate/Resource/robots.txt
sanic_boot/projectTemplate/Tasks/__init__.py
sanic_boot/projectTemplate/Views/__init__.py
sanic_boot-0.0.4.dist-info/METADATA
sanic_boot-0.0.4.dist-info/WHEEL
sanic_boot-0.0.4.dist-info/entry_points.txt
sanic_boot-0.0.4.dist-info/licenses/LICENSE
sanic_boot-0.0.4.dist-info/RECORD
