Metadata-Version: 2.4
Name: sanic-boot
Version: 0.0.4
Summary: A web framework base on Sanic
Author-email: 嬴寒 <yinghan22@163.com>
License-File: LICENSE
Requires-Python: >=3.9
Requires-Dist: sanic<=24.6
Requires-Dist: tortoise-orm<=0.21.4
